pyweb_db/__init__.py
pyweb_db/main.py
pyweb_db-1.0.6.dist-info/LICENSE
pyweb_db-1.0.6.dist-info/METADATA
pyweb_db-1.0.6.dist-info/WHEEL
pyweb_db-1.0.6.dist-info/top_level.txt
pyweb_db-1.0.6.dist-info/RECORD
